senzing/G2Config.py
senzing/G2ConfigMgr.py
senzing/G2Diagnostic.py
senzing/G2Engine.py
senzing/G2EngineFlags.py
senzing/G2Exception.py
senzing/G2Hasher.py
senzing/G2Product.py
senzing/__init__.py
senzing_ce-3.3.0.dist-info/LICENSE
senzing_ce-3.3.0.dist-info/METADATA
senzing_ce-3.3.0.dist-info/WHEEL
senzing_ce-3.3.0.dist-info/top_level.txt
senzing_ce-3.3.0.dist-info/RECORD
