Metadata-Version: 2.1
Name: senzing-ce
Version: 3.3.0
Summary: Python SDK for Senzing API
Home-page: https://github.com/Senzing/g2-sdk-python
Author: senzing
Author-email: support@senzing.com
License: Apache 2
Project-URL: Bug Tracker, https://github.com/Senzing/g2-sdk-python/issues
Classifier: Programming Language :: Python :: 3
Classifier: License :: OSI Approved :: Apache Software License
Classifier: Operating System :: OS Independent
Requires-Python: >=3.6
License-File: LICENSE
